LICENSE
ask_lang/__init__.py
ask_lang/__main__.py
ask_lang/cfg.py
ask_lang/tests/__init__.py
ask_lang/tests/test__main__.py
ask_lang/tests/transpiler/__init__.py
ask_lang/tests/transpiler/test_lexer.py
ask_lang/tests/transpiler/test_translator.py
ask_lang/tests/transpiler/utilities/__init__.py
ask_lang/tests/transpiler/utilities/test_lexer_utils.py
ask_lang/tests/transpiler/utilities/test_small_transpilers.py
ask_lang/tests/transpiler/utilities/test_translator_utils.py
ask_lang/tests/transpiler/utilities/test_transpiler_utils.py
ask_lang/tests/utilities/__init__.py
ask_lang/tests/utilities/test_askfile.py
ask_lang/tests/utilities/test_files.py
ask_lang/transpiler/__init__.py
ask_lang/transpiler/errors.py
ask_lang/transpiler/lexer.py
ask_lang/transpiler/translator.py
ask_lang/transpiler/transpiler.py
ask_lang/transpiler/utilities/__init__.py
ask_lang/transpiler/utilities/lexer_utils.py
ask_lang/transpiler/utilities/small_transpilers.py
ask_lang/transpiler/utilities/translator_utils.py
ask_lang/transpiler/utilities/transpiler_utils.py
ask_lang/utilities/__init__.py
ask_lang/utilities/askfile.py
ask_lang/utilities/files.py
ask_lang/utilities/printing.py
ask_lang/utilities/serve_run.py
ask_lang-1.5.0.dist-info/LICENSE
ask_lang-1.5.0.dist-info/METADATA
ask_lang-1.5.0.dist-info/WHEEL
ask_lang-1.5.0.dist-info/entry_points.txt
ask_lang-1.5.0.dist-info/RECORD
