Metadata-Version: 2.1
Name: ask_lang
Version: 1.5.0
Summary: Ask is a modern open-source transpiled programming language, designed for building backend services and APIs. Ask reduces the amount of needed boilerplate code for setting up things like database connections and authentication to virtually zero lines.
Home-page: https://ask.edvard.dev
License: GNU GPL v3.0
Keywords: ask,programming language,backend,api,rest,tool
Author: Edvard Busck-Nielsen
Author-email: me@edvard.dev
Requires-Python: >=3.8,<4.0
Classifier: Development Status :: 4 - Beta
Classifier: Environment :: Console
Classifier: Framework :: Flask
Classifier: License :: OSI Approved :: GNU General Public License v3 or later (GPLv3+)
Classifier: License :: Other/Proprietary License
Classifier: Operating System :: OS Independent
Classifier: Programming Language :: Python :: 3
Classifier: Programming Language :: Python :: 3.8
Classifier: Programming Language :: Python :: 3.9
Classifier: Programming Language :: Python :: 3.10
Classifier: Programming Language :: Python :: 3.11
Classifier: Programming Language :: Python :: 3.12
Classifier: Topic :: Software Development
Classifier: Topic :: Software Development :: Build Tools
Classifier: Topic :: Software Development :: Code Generators
Classifier: Topic :: Software Development :: Compilers
Classifier: Topic :: Software Development :: Pre-processors
Classifier: Topic :: Software Development :: Version Control :: Git
Requires-Dist: Flask (>=3.0.3,<4.0.0)
Requires-Dist: Flask-Cors (>=3.0.10,<6.0.0)
Requires-Dist: Flask-Limiter (>=3.8.0,<4.0.0)
Requires-Dist: Flask-Mail (>=0.10.0,<0.11.0)
Requires-Dist: Flask-SQLAlchemy (>=3.1.1,<4.0.0)
Requires-Dist: Flask-Selfdoc (>=1.2.3,<2.0.0)
Requires-Dist: Jinja2 (>=3.1.2)
Requires-Dist: Paste (>=3.5.0,<4.0.0)
Requires-Dist: PyJWT (>=2.9.0,<3.0.0)
Requires-Dist: PyMySQL (>=1.0.2,<2.0.0)
Requires-Dist: SQLAlchemy (>=2.0.16)
Requires-Dist: abnex (==1.0.2)
Requires-Dist: coverage (>=7.6.1,<8.0.0)
Requires-Dist: limits (>=3.13)
Requires-Dist: requests (>=2.25.1,<3.0.0)
Requires-Dist: six (>=1.15.0,<2.0.0)
Requires-Dist: tabulate (>=0.9.0,<0.10.0)
Requires-Dist: toml (>=0.10.2,<0.11.0)
Requires-Dist: waitress (>=3.0.0,<4.0.0)
Project-URL: Repository, https://github.com/Buscedv/Ask
